LICENSE.txt
MANIFEST.in
README.md
setup.py
widget-example.png
django_ordered_m2m.egg-info/PKG-INFO
django_ordered_m2m.egg-info/SOURCES.txt
django_ordered_m2m.egg-info/dependency_links.txt
django_ordered_m2m.egg-info/top_level.txt
ordered_m2m/__init__.py
ordered_m2m/admin.py
ordered_m2m/fields.py
ordered_m2m/models.py
ordered_m2m/settings.py
ordered_m2m/widgets.py
ordered_m2m/static/ordered_m2m/widget.css
ordered_m2m/static/ordered_m2m/widget.js